Workbook

Sheet Painel
A1: Indicador | B1: Valor
A2: Veículos cadastrados | B2: =COUNTA('Cadastro Frota'!A2:A5) -> 4
A3: KM rodados registrados | B3: =SUM('Viagens e KM'!K2:K101) -> 0
A4: Total abastecimento (R$) | B4: =SUM(Abastecimentos!F2:F101) -> 0
A5: Litros abastecidos | B5: =SUM(Abastecimentos!E2:E101) -> 0
A6: Custo manutenção (R$) | B6: =SUM(Manutenções!G2:G101) -> 0
A7: Custo total (R$) | B7: =B4+B6 -> 0
A8: Checklists com pendência | B8: =COUNTIF(Checklist!L2:L101,"PENDÊNCIA") -> 0
A9: Documentos vencidos | B9: =COUNTIF(Documentos!E2:E101,"VENCIDO") -> 0
A10: Documentos próximos (30 dias) | B10: =COUNTIF(Documentos!E2:E101,"ATENÇÃO") -> 0
A11: Manutenções planejadas | B11: =COUNTIF(Manutenções!J2:J101,"Planejada") -> 0
A13: Veículo | B13: KM rodados | C13: Abastecimento R$ | D13: Manutenção R$
A14: V01 | B14: =SUMIF('Viagens e KM'!B2:B101,A14,'Viagens e KM'!K2:K101) -> 0 | C14: =SUMIF(Abastecimentos!B2:B101,A14,Abastecimentos!F2:F101) -> 0 | D14: =SUMIF(Manutenções!B2:B101,A14,Manutenções!G2:G101) -> 0
A15: V02 | B15: =SUMIF('Viagens e KM'!B2:B101,A15,'Viagens e KM'!K2:K101) -> 0 | C15: =SUMIF(Abastecimentos!B2:B101,A15,Abastecimentos!F2:F101) -> 0 | D15: =SUMIF(Manutenções!B2:B101,A15,Manutenções!G2:G101) -> 0
A16: V03 | B16: =SUMIF('Viagens e KM'!B2:B101,A16,'Viagens e KM'!K2:K101) -> 0 | C16: =SUMIF(Abastecimentos!B2:B101,A16,Abastecimentos!F2:F101) -> 0 | D16: =SUMIF(Manutenções!B2:B101,A16,Manutenções!G2:G101) -> 0
A17: C01 | B17: =SUMIF('Viagens e KM'!B2:B101,A17,'Viagens e KM'!K2:K101) -> 0 | C17: =SUMIF(Abastecimentos!B2:B101,A17,Abastecimentos!F2:F101) -> 0 | D17: =SUMIF(Manutenções!B2:B101,A17,Manutenções!G2:G101) -> 0

Sheet Cadastro Frota
A1: ID Veículo | B1: Tipo | C1: Modelo | D1: Placa | E1: Ano | F1: KM Atual | G1: Responsável | H1: Próxima Revisão KM | I1: Próxima Revisão Data | J1: Situação
A2: V01 | B2: Leve | J2: Ativo
A3: V02 | B3: Leve | J3: Ativo
A4: V03 | B4: Leve | J4: Ativo
A5: C01 | B5: Caminhão | J5: Ativo

Sheet Viagens e KM
A1: Data | B1: Veículo | C1: Condutor | D1: Finalidade | E1: Origem | F1: Destino | G1: Saída | H1: Retorno | I1: KM Inicial | J1: KM Final | K1: KM Percorrido | L1: Observações
K2: =IF(OR(I2="",J2=""),"",IF(J2>=I2,J2-I2,"VERIFICAR KM"))
K3: =IF(OR(I3="",J3=""),"",IF(J3>=I3,J3-I3,"VERIFICAR KM"))
K4: =IF(OR(I4="",J4=""),"",IF(J4>=I4,J4-I4,"VERIFICAR KM"))
K5: =IF(OR(I5="",J5=""),"",IF(J5>=I5,J5-I5,"VERIFICAR KM"))
K6: =IF(OR(I6="",J6=""),"",IF(J6>=I6,J6-I6,"VERIFICAR KM"))
K7: =IF(OR(I7="",J7=""),"",IF(J7>=I7,J7-I7,"VERIFICAR KM"))
K8: =IF(OR(I8="",J8=""),"",IF(J8>=I8,J8-I8,"VERIFICAR KM"))
K9: =IF(OR(I9="",J9=""),"",IF(J9>=I9,J9-I9,"VERIFICAR KM"))
K10: =IF(OR(I10="",J10=""),"",IF(J10>=I10,J10-I10,"VERIFICAR KM"))
K11: =IF(OR(I11="",J11=""),"",IF(J11>=I11,J11-I11,"VERIFICAR KM"))
K12: =IF(OR(I12="",J12=""),"",IF(J12>=I12,J12-I12,"VERIFICAR KM"))
K13: =IF(OR(I13="",J13=""),"",IF(J13>=I13,J13-I13,"VERIFICAR KM"))
... K101: =IF(OR(I101="",J101=""),"",IF(J101>=I101,J101-I101,"VERIFICAR KM"))

Sheet Checklist
A1: Data | B1: Veículo | C1: Condutor | D1: Pneus | E1: Óleo | F1: Água | G1: Freios | H1: Luzes | I1: Documentos | J1: Limpeza | K1: Avarias | L1: Status Geral | M1: Observações
L2: =IF(B2="","",IF(COUNTIF(D2:K2,"Não conforme")>0,"PENDÊNCIA",IF(COUNTA(D2:K2)<8,"INCOMPLETO","OK")))
L3: =IF(B3="","",IF(COUNTIF(D3:K3,"Não conforme")>0,"PENDÊNCIA",IF(COUNTA(D3:K3)<8,"INCOMPLETO","OK")))
L4: =IF(B4="","",IF(COUNTIF(D4:K4,"Não conforme")>0,"PENDÊNCIA",IF(COUNTA(D4:K4)<8,"INCOMPLETO","OK")))
L5: =IF(B5="","",IF(COUNTIF(D5:K5,"Não conforme")>0,"PENDÊNCIA",IF(COUNTA(D5:K5)<8,"INCOMPLETO","OK")))
L6: =IF(B6="","",IF(COUNTIF(D6:K6,"Não conforme")>0,"PENDÊNCIA",IF(COUNTA(D6:K6)<8,"INCOMPLETO","OK")))
L7: =IF(B7="","",IF(COUNTIF(D7:K7,"Não conforme")>0,"PENDÊNCIA",IF(COUNTA(D7:K7)<8,"INCOMPLETO","OK")))
L8: =IF(B8="","",IF(COUNTIF(D8:K8,"Não conforme")>0,"PENDÊNCIA",IF(COUNTA(D8:K8)<8,"INCOMPLETO","OK")))
L9: =IF(B9="","",IF(COUNTIF(D9:K9,"Não conforme")>0,"PENDÊNCIA",IF(COUNTA(D9:K9)<8,"INCOMPLETO","OK")))
L10: =IF(B10="","",IF(COUNTIF(D10:K10,"Não conforme")>0,"PENDÊNCIA",IF(COUNTA(D10:K10)<8,"INCOMPLETO","OK")))
L11: =IF(B11="","",IF(COUNTIF(D11:K11,"Não conforme")>0,"PENDÊNCIA",IF(COUNTA(D11:K11)<8,"INCOMPLETO","OK")))
L12: =IF(B12="","",IF(COUNTIF(D12:K12,"Não conforme")>0,"PENDÊNCIA",IF(COUNTA(D12:K12)<8,"INCOMPLETO","OK")))
L13: =IF(B13="","",IF(COUNTIF(D13:K13,"Não conforme")>0,"PENDÊNCIA",IF(COUNTA(D13:K13)<8,"INCOMPLETO","OK")))
... L101: =IF(B101="","",IF(COUNTIF(D101:K101,"Não conforme")>0,"PENDÊNCIA",IF(COUNTA(D101:K101)<8,"INCOMPLETO","OK")))

Sheet Abastecimentos
A1: Data | B1: Veículo | C1: Condutor | D1: KM | E1: Litros | F1: Valor Total R$ | G1: Preço por Litro | H1: KM desde Abastec. Anterior | I1: Consumo km/L | J1: Posto | K1: Observações
G2: =IF(OR(E2="",F2=""),"",IFERROR(F2/E2,""))
G3: =IF(OR(E3="",F3=""),"",IFERROR(F3/E3,""))
G4: =IF(OR(E4="",F4=""),"",IFERROR(F4/E4,""))
G5: =IF(OR(E5="",F5=""),"",IFERROR(F5/E5,""))
G6: =IF(OR(E6="",F6=""),"",IFERROR(F6/E6,""))
G7: =IF(OR(E7="",F7=""),"",IFERROR(F7/E7,""))
G8: =IF(OR(E8="",F8=""),"",IFERROR(F8/E8,""))
G9: =IF(OR(E9="",F9=""),"",IFERROR(F9/E9,""))
G10: =IF(OR(E10="",F10=""),"",IFERROR(F10/E10,""))
G11: =IF(OR(E11="",F11=""),"",IFERROR(F11/E11,""))
G12: =IF(OR(E12="",F12=""),"",IFERROR(F12/E12,""))
G13: =IF(OR(E13="",F13=""),"",IFERROR(F13/E13,""))
... G101: =IF(OR(E101="",F101=""),"",IFERROR(F101/E101,""))

Sheet Manutenções
A1: Data | B1: Veículo | C1: Tipo | D1: Serviço | E1: Fornecedor | F1: KM Serviço | G1: Custo R$ | H1: Próxima Revisão KM | I1: Próxima Revisão Data | J1: Status | K1: Observações

Sheet Documentos
A1: Veículo | B1: Documento | C1: Vencimento | D1: Dias até Vencer | E1: Status | F1: Observações
D2: =IF(C2="","",C2-TODAY()) | E2: =IF(C2="","",IF(D2<0,"VENCIDO",IF(D2<=30,"ATENÇÃO","EM DIA")))
D3: =IF(C3="","",C3-TODAY()) | E3: =IF(C3="","",IF(D3<0,"VENCIDO",IF(D3<=30,"ATENÇÃO","EM DIA")))
D4: =IF(C4="","",C4-TODAY()) | E4: =IF(C4="","",IF(D4<0,"VENCIDO",IF(D4<=30,"ATENÇÃO","EM DIA")))
D5: =IF(C5="","",C5-TODAY()) | E5: =IF(C5="","",IF(D5<0,"VENCIDO",IF(D5<=30,"ATENÇÃO","EM DIA")))
D6: =IF(C6="","",C6-TODAY()) | E6: =IF(C6="","",IF(D6<0,"VENCIDO",IF(D6<=30,"ATENÇÃO","EM DIA")))
D7: =IF(C7="","",C7-TODAY()) | E7: =IF(C7="","",IF(D7<0,"VENCIDO",IF(D7<=30,"ATENÇÃO","EM DIA")))
D8: =IF(C8="","",C8-TODAY()) | E8: =IF(C8="","",IF(D8<0,"VENCIDO",IF(D8<=30,"ATENÇÃO","EM DIA")))
D9: =IF(C9="","",C9-TODAY()) | E9: =IF(C9="","",IF(D9<0,"VENCIDO",IF(D9<=30,"ATENÇÃO","EM DIA")))
D10: =IF(C10="","",C10-TODAY()) | E10: =IF(C10="","",IF(D10<0,"VENCIDO",IF(D10<=30,"ATENÇÃO","EM DIA")))
D11: =IF(C11="","",C11-TODAY()) | E11: =IF(C11="","",IF(D11<0,"VENCIDO",IF(D11<=30,"ATENÇÃO","EM DIA")))
D12: =IF(C12="","",C12-TODAY()) | E12: =IF(C12="","",IF(D12<0,"VENCIDO",IF(D12<=30,"ATENÇÃO","EM DIA")))
D13: =IF(C13="","",C13-TODAY()) | E13: =IF(C13="","",IF(D13<0,"VENCIDO",IF(D13<=30,"ATENÇÃO","EM DIA")))
... D101: =IF(C101="","",C101-TODAY()) | E101: =IF(C101="","",IF(D101<0,"VENCIDO",IF(D101<=30,"ATENÇÃO","EM DIA")))

Sheet Instruções
A1: Tema | B1: Orientação
A2: Primeiros passos | B2: Preencha modelo, placa, KM atual e revisão dos quatro veículos na aba Cadastro Frota.
A3: Saídas e retornos | B3: Registre toda viagem, inclusive transporte de colaboradores. O KM percorrido é automático.
A4: Checklist | B4: Faça antes da utilização. Marque Conforme, Não conforme ou N/A em todos os itens.
A5: Ocorrências | B5: Registre avarias e comunique ao gestor. Não libere veículo inseguro.
A6: Abastecimento | B6: Lance data, KM, litros e custo de cada abastecimento.
A7: Manutenção | B7: Registre serviço, custo, KM e próxima revisão. Atualize cadastro da frota.
A8: Documentação | B8: Cadastre vencimentos de licenciamento, seguro e outros documentos relevantes.
A9: Responsabilidades | B9: Motorista centraliza controles; outros condutores preenchem suas viagens e informam falhas; gestor aprova despesas.
A10: Observação | B10: Painel mostra lançamentos, não representa histórico anterior ao início do controle.
A11: Capacidade | B11: Modelo com 100 linhas de lançamento por aba; amplie fórmulas ao ultrapassar esse limite.
